pykivdroid/__init__.py
pykivdroid/brightness.py
pykivdroid/orientation.py
pykivdroid/picker.py
pykivdroid/screen.py
pykivdroid/stt.py
pykivdroid/tts.py
pykivdroid/unityads.py
pykivdroid/videoview.py
pykivdroid-0.0.2.dist-info/METADATA
pykivdroid-0.0.2.dist-info/RECORD
pykivdroid-0.0.2.dist-info/WHEEL
pykivdroid-0.0.2.dist-info/top_level.txt
