Metadata-Version: 2.1
Name: pykivdroid
Version: 0.0.2
Summary: Python tools to control android
Home-page: https://github.com/Sahil-pixel/Pykivdroid
Author: SK SAHIL
License: MIT
Keywords: python,kivy,android,pyjnius
Platform: UNKNOWN
Requires-Dist: kivy
Requires-Dist: pyjnius
Requires-Dist: android
